[
  {
    "id": "np34yhrozypsu45",
    "name": "decks",
    "type": "base",
    "system": false,
    "schema": [
      {
        "system": false,
        "id": "3e836e49",
        "name": "user_id",
        "type": "relation",
        "required": true,
        "presentable": false,
        "unique": false,
        "options": {
          "collectionId": "_pb_users_auth_",
          "cascadeDelete": false,
          "minSelect": null,
          "maxSelect": 1,
          "displayFields": null
        }
      },
      {
        "system": false,
        "id": "srzsvzyu",
        "name": "name",
        "type": "text",
        "required": true,
        "presentable": false,
        "unique": false,
        "options": {
          "min": null,
          "max": null,
          "pattern": ""
        }
      },
      {
        "system": false,
        "id": "fc06ynpy",
        "name": "description",
        "type": "text",
        "required": false,
        "presentable": false,
        "unique": false,
        "options": {
          "min": null,
          "max": null,
          "pattern": ""
        }
      },
      {
        "system": false,
        "id": "giwdtqet",
        "name": "options",
        "type": "json",
        "required": false,
        "presentable": false,
        "unique": false,
        "options": {
          "maxSize": 2000000
        }
      },
      {
        "system": false,
        "id": "vvimj5zv",
        "name": "public",
        "type": "bool",
        "required": false,
        "presentable": false,
        "unique": false,
        "options": {}
      }
    ],
    "indexes": [],
    "listRule": "(@request.auth.id = user_id) || (public = true)",
    "viewRule": "(@request.auth.id = user_id) || (public = true)",
    "createRule": "@request.auth.id != \"\"",
    "updateRule": "@request.auth.id = user_id",
    "deleteRule": "@request.auth.id = user_id",
    "options": {}
  },
  {
    "id": "zifjnwldx56ugu1",
    "name": "passages",
    "type": "base",
    "system": false,
    "schema": [
      {
        "system": false,
        "id": "t5ujkv2s",
        "name": "deck_id",
        "type": "relation",
        "required": false,
        "presentable": false,
        "unique": false,
        "options": {
          "collectionId": "np34yhrozypsu45",
          "cascadeDelete": false,
          "minSelect": null,
          "maxSelect": 1,
          "displayFields": null
        }
      },
      {
        "system": false,
        "id": "ee2la5bv",
        "name": "verses_kjv",
        "type": "relation",
        "required": false,
        "presentable": false,
        "unique": false,
        "options": {
          "collectionId": "vueer34y6xi0b2n",
          "cascadeDelete": false,
          "minSelect": null,
          "maxSelect": null,
          "displayFields": null
        }
      },
      {
        "system": false,
        "id": "t3ro1exj",
        "name": "notes",
        "type": "text",
        "required": false,
        "presentable": false,
        "unique": false,
        "options": {
          "min": null,
          "max": null,
          "pattern": ""
        }
      },
      {
        "system": false,
        "id": "0wruup2n",
        "name": "srs_due",
        "type": "date",
        "required": false,
        "presentable": false,
        "unique": false,
        "options": {
          "min": "",
          "max": ""
        }
      },
      {
        "system": false,
        "id": "ydejzeeg",
        "name": "srs_stability",
        "type": "number",
        "required": false,
        "presentable": false,
        "unique": false,
        "options": {
          "min": null,
          "max": null,
          "noDecimal": false
        }
      },
      {
        "system": false,
        "id": "vm1apfwa",
        "name": "srs_difficulty",
        "type": "number",
        "required": false,
        "presentable": false,
        "unique": false,
        "options": {
          "min": null,
          "max": null,
          "noDecimal": false
        }
      },
      {
        "system": false,
        "id": "uxkysk8u",
        "name": "srs_elapsed_days",
        "type": "number",
        "required": false,
        "presentable": false,
        "unique": false,
        "options": {
          "min": null,
          "max": null,
          "noDecimal": true
        }
      },
      {
        "system": false,
        "id": "hdevltpz",
        "name": "srs_scheduled_days",
        "type": "number",
        "required": false,
        "presentable": false,
        "unique": false,
        "options": {
          "min": null,
          "max": null,
          "noDecimal": true
        }
      },
      {
        "system": false,
        "id": "dammr8iy",
        "name": "srs_reps",
        "type": "number",
        "required": false,
        "presentable": false,
        "unique": false,
        "options": {
          "min": null,
          "max": null,
          "noDecimal": true
        }
      },
      {
        "system": false,
        "id": "bri45sbm",
        "name": "srs_lapses",
        "type": "number",
        "required": false,
        "presentable": false,
        "unique": false,
        "options": {
          "min": null,
          "max": null,
          "noDecimal": true
        }
      },
      {
        "system": false,
        "id": "m19lmnqt",
        "name": "srs_state",
        "type": "select",
        "required": false,
        "presentable": false,
        "unique": false,
        "options": {
          "maxSelect": 1,
          "values": ["New", "Learning", "Review", "Relearning"]
        }
      },
      {
        "system": false,
        "id": "jkylakzv",
        "name": "srs_last_review",
        "type": "date",
        "required": false,
        "presentable": false,
        "unique": false,
        "options": {
          "min": "",
          "max": ""
        }
      }
    ],
    "indexes": [],
    "listRule": "(@request.auth.id = deck_id.user_id) || (deck_id.public = true)",
    "viewRule": "(@request.auth.id = deck_id.user_id) || (deck_id.public = true)",
    "createRule": "@request.auth.id != \"\"",
    "updateRule": "@request.auth.id = deck_id.user_id",
    "deleteRule": "@request.auth.id = deck_id.user_id",
    "options": {}
  },
  {
    "id": "vueer34y6xi0b2n",
    "name": "t_kjv",
    "type": "base",
    "system": false,
    "schema": [
      {
        "system": false,
        "id": "7vzxpvgx",
        "name": "key",
        "type": "number",
        "required": false,
        "presentable": false,
        "unique": false,
        "options": {
          "min": null,
          "max": null,
          "noDecimal": true
        }
      },
      {
        "system": false,
        "id": "izfwrpjm",
        "name": "t",
        "type": "text",
        "required": false,
        "presentable": false,
        "unique": false,
        "options": {
          "min": null,
          "max": null,
          "pattern": ""
        }
      },
      {
        "system": false,
        "id": "aofjybxe",
        "name": "b",
        "type": "number",
        "required": false,
        "presentable": false,
        "unique": false,
        "options": {
          "min": null,
          "max": null,
          "noDecimal": false
        }
      },
      {
        "system": false,
        "id": "rn7b22hs",
        "name": "c",
        "type": "number",
        "required": false,
        "presentable": false,
        "unique": false,
        "options": {
          "min": null,
          "max": null,
          "noDecimal": false
        }
      },
      {
        "system": false,
        "id": "ocwib7ng",
        "name": "v",
        "type": "number",
        "required": false,
        "presentable": false,
        "unique": false,
        "options": {
          "min": null,
          "max": null,
          "noDecimal": false
        }
      }
    ],
    "indexes": ["CREATE INDEX `t_kjv_key` ON `t_kjv` (`key`)"],
    "listRule": "",
    "viewRule": "",
    "createRule": null,
    "updateRule": null,
    "deleteRule": null,
    "options": {}
  },
  {
    "id": "_pb_users_auth_",
    "name": "users",
    "type": "auth",
    "system": false,
    "schema": [
      {
        "system": false,
        "id": "users_name",
        "name": "name",
        "type": "text",
        "required": false,
        "presentable": false,
        "unique": false,
        "options": {
          "min": null,
          "max": null,
          "pattern": ""
        }
      },
      {
        "system": false,
        "id": "users_avatar",
        "name": "avatar",
        "type": "file",
        "required": false,
        "presentable": false,
        "unique": false,
        "options": {
          "mimeTypes": [
            "image/jpeg",
            "image/png",
            "image/svg+xml",
            "image/gif",
            "image/webp"
          ],
          "thumbs": null,
          "maxSelect": 1,
          "maxSize": 5242880,
          "protected": false
        }
      }
    ],
    "indexes": [],
    "listRule": "id = @request.auth.id",
    "viewRule": "id = @request.auth.id",
    "createRule": "",
    "updateRule": "id = @request.auth.id",
    "deleteRule": "id = @request.auth.id",
    "options": {
      "allowEmailAuth": true,
      "allowOAuth2Auth": true,
      "allowUsernameAuth": true,
      "exceptEmailDomains": null,
      "manageRule": null,
      "minPasswordLength": 8,
      "onlyEmailDomains": null,
      "onlyVerified": false,
      "requireEmail": false
    }
  }
]
